LICENSE
MANIFEST.in
README.rst
setup.cfg
setup.py
setuphelp.py
docs/Makefile
docs/make.bat
docs/c_include/Doxyfile
docs/source/InputReader.rst
docs/source/Namespace.rst
docs/source/ReaderError.rst
docs/source/SUPPRESS.rst
docs/source/c_api.rst
docs/source/changelog.rst
docs/source/conf.py
docs/source/helperfunctions.rst
docs/source/index.rst
docs/source/intro.rst
docs/source/subclassing.rst
input_reader/__init__.py
input_reader/__init__.pyc
input_reader/_version.py
input_reader/_version.pyc
input_reader/files.py
input_reader/files.pyc
input_reader/helpers.py
input_reader/helpers.pyc
input_reader/input_reader.py
input_reader/input_reader.pyc
input_reader/key_adder.py
input_reader/key_adder.pyc
input_reader/keylevel.py
input_reader/keylevel.pyc
input_reader/py23compat.py
input_reader/py23compat.pyc
input_reader.egg-info/PKG-INFO
input_reader.egg-info/SOURCES.txt
input_reader.egg-info/dependency_links.txt
input_reader.egg-info/top_level.txt
input_reader/include/input_reader.h
input_reader/tests/test_block.py
input_reader/tests/test_boolean.py
input_reader/tests/test_constructor.py
input_reader/tests/test_files.py
input_reader/tests/test_keywords.py
input_reader/tests/test_line.py
input_reader/tests/test_mutually_excusive_group.py
input_reader/tests/test_namespece.py
input_reader/tests/test_read_file.py
input_reader/tests/test_regex.py
input_reader/tests/test_sublcass.py