Metadata-Version: 1.1
Name: input_reader
Version: 1.2.2
Summary: Define and read input files with an API inspired by argparse
Home-page: https://github.com/SethMMorton/input_reader
Author: Seth M. Morton
Author-email: drtuba78@gmail.com
License: MIT
Platform: UNKNOWN
Classifier: Development Status :: 5 - Production/Stable
Classifier: Intended Audience :: Developers
Classifier: Intended Audience :: Science/Research
Classifier: Operating System :: OS Independent
Classifier: License :: OSI Approved :: MIT License
Classifier: Natural Language :: English
Classifier: Programming Language :: Python :: 2.6
Classifier: Programming Language :: Python :: 2.7
Classifier: Programming Language :: Python :: 3
Classifier: Topic :: Scientific/Engineering
Classifier: Topic :: Utilities
